IrisKuangjiaZhongwenWendangFix1/README.md
IrisKuangjiaZhongwenWendangFix1/__init__.py
IrisKuangjiaZhongwenWendangFix1/__main__.py
IrisKuangjiaZhongwenWendangFix1/file.epub
IrisKuangjiaZhongwenWendangFix1/index.html
IrisKuangjiaZhongwenWendangFix1/css/__init__.py
IrisKuangjiaZhongwenWendangFix1/css/annotations.css
IrisKuangjiaZhongwenWendangFix1/css/main.css
IrisKuangjiaZhongwenWendangFix1/css/normalize.css
IrisKuangjiaZhongwenWendangFix1/css/popup.css
IrisKuangjiaZhongwenWendangFix1/font/__init__.py
IrisKuangjiaZhongwenWendangFix1/font/fontello.eot
IrisKuangjiaZhongwenWendangFix1/font/fontello.svg
IrisKuangjiaZhongwenWendangFix1/font/fontello.ttf
IrisKuangjiaZhongwenWendangFix1/font/fontello.woff
IrisKuangjiaZhongwenWendangFix1/img/__init__.py
IrisKuangjiaZhongwenWendangFix1/img/annotator-glyph-sprite.png
IrisKuangjiaZhongwenWendangFix1/img/annotator-icon-sprite.png
IrisKuangjiaZhongwenWendangFix1/img/apple-touch-icon.png
IrisKuangjiaZhongwenWendangFix1/img/cancelfullscreen.png
IrisKuangjiaZhongwenWendangFix1/img/close.png
IrisKuangjiaZhongwenWendangFix1/img/fullscreen.png
IrisKuangjiaZhongwenWendangFix1/img/loader.gif
IrisKuangjiaZhongwenWendangFix1/img/menu-icon.png
IrisKuangjiaZhongwenWendangFix1/img/save.png
IrisKuangjiaZhongwenWendangFix1/img/saved.png
IrisKuangjiaZhongwenWendangFix1/img/settings-s.png
IrisKuangjiaZhongwenWendangFix1/img/settings.png
IrisKuangjiaZhongwenWendangFix1/img/star.png
IrisKuangjiaZhongwenWendangFix1/js/__init__.py
IrisKuangjiaZhongwenWendangFix1/js/epub.js
IrisKuangjiaZhongwenWendangFix1/js/epub.min.js
IrisKuangjiaZhongwenWendangFix1/js/epub.min.map
IrisKuangjiaZhongwenWendangFix1/js/hooks.min.js
IrisKuangjiaZhongwenWendangFix1/js/hooks.min.map
IrisKuangjiaZhongwenWendangFix1/js/reader.js
IrisKuangjiaZhongwenWendangFix1/js/reader.js.map
IrisKuangjiaZhongwenWendangFix1/js/reader.min.js
IrisKuangjiaZhongwenWendangFix1/js/reader.min.map
IrisKuangjiaZhongwenWendangFix1/js/hooks/__init__.py
iris_kuangjia_zhongwen_wendang_fix1-2025.3.25.1.dist-info/METADATA
iris_kuangjia_zhongwen_wendang_fix1-2025.3.25.1.dist-info/WHEEL
iris_kuangjia_zhongwen_wendang_fix1-2025.3.25.1.dist-info/entry_points.txt
iris_kuangjia_zhongwen_wendang_fix1-2025.3.25.1.dist-info/top_level.txt
iris_kuangjia_zhongwen_wendang_fix1-2025.3.25.1.dist-info/RECORD
